alicorn_sqlalchemy/__init__.py
alicorn_sqlalchemy/_version.py
alicorn_sqlalchemy-0.0.1.dist-info/METADATA
alicorn_sqlalchemy-0.0.1.dist-info/WHEEL
alicorn_sqlalchemy-0.0.1.dist-info/top_level.txt
alicorn_sqlalchemy-0.0.1.dist-info/RECORD
